pyheap/__init__.py
pyheap/comparablevalue.py
pyheap/heap.py
pyheap/heap_test.py
pyheap_elunico-0.5.0.dist-info/METADATA
pyheap_elunico-0.5.0.dist-info/WHEEL
pyheap_elunico-0.5.0.dist-info/top_level.txt
pyheap_elunico-0.5.0.dist-info/RECORD
