Metadata-Version: 2.1
Name: pyheap-elunico
Version: 0.5.0
Summary: A wrapper class around Python's built-in heapq module
Home-page: https://github.com/elunico/pyheap
Author: Thomas Povinelli
Author-email: tompov227@gmail.com
Classifier: Programming Language :: Python :: 3
Classifier: License :: OSI Approved :: MIT License
Classifier: Operating System :: OS Independent
Requires-Python: >=3.11
